HISTORY.txt
README.rst
setup.py
corejet/__init__.py
corejet.robot.egg-info/PKG-INFO
corejet.robot.egg-info/SOURCES.txt
corejet.robot.egg-info/dependency_links.txt
corejet.robot.egg-info/entry_points.txt
corejet.robot.egg-info/namespace_packages.txt
corejet.robot.egg-info/not-zip-safe
corejet.robot.egg-info/requires.txt
corejet.robot.egg-info/top_level.txt
corejet/robot/__init__.py
corejet/robot/scripts/__init__.py
corejet/robot/scripts/corejet2robot.py
corejet/robot/xslt/corejet-to-robot.xsl