Metadata-Version: 1.0
Name: corejet.robot
Version: 0.5.0
Summary: Robot Framework support for CoreJet
Home-page: https://github.com/datakurre/corejet.robot/
Author: Asko Soukka
Author-email: asko.soukka@iki.fi
License: GPL
Platform: UNKNOWN
Classifier: Programming Language :: Python
